LICENSE
MANIFEST.in
README.md
doc_requirements.txt
requirements.txt
setup.cfg
setup.py
test_requirements.txt
DynamicAnnotationDB.egg-info/PKG-INFO
DynamicAnnotationDB.egg-info/SOURCES.txt
DynamicAnnotationDB.egg-info/dependency_links.txt
DynamicAnnotationDB.egg-info/requires.txt
DynamicAnnotationDB.egg-info/top_level.txt
dynamicannotationdb/__init__.py
dynamicannotationdb/annotation.py
dynamicannotationdb/database.py
dynamicannotationdb/errors.py
dynamicannotationdb/interface.py
dynamicannotationdb/key_utils.py
dynamicannotationdb/models.py
dynamicannotationdb/schema.py
dynamicannotationdb/segmentation.py
dynamicannotationdb/migration/__init__.py
dynamicannotationdb/migration/migrate.py
dynamicannotationdb/migration/alembic/__init__.py
dynamicannotationdb/migration/alembic/env.py
dynamicannotationdb/migration/alembic/run.py
dynamicannotationdb/migration/alembic/versions/309cf493a1e2_adding_warning_field.py
dynamicannotationdb/migration/alembic/versions/5a1d7c0ad006_add_status_column.py
dynamicannotationdb/migration/alembic/versions/6e7f580ff680_add_error_msg.py
dynamicannotationdb/migration/alembic/versions/7c79eff751b4_add_parent_version_column.py
dynamicannotationdb/migration/alembic/versions/814d72d74e3b_add_version_error_table.py
dynamicannotationdb/migration/alembic/versions/8fdc843fc202_adding_permission_and_last_modified.py
dynamicannotationdb/migration/alembic/versions/975a79461cab_add_is_merged.py
dynamicannotationdb/migration/alembic/versions/__init__.py
dynamicannotationdb/migration/alembic/versions/ef5c2d7f96d8_initial_live_db_models.py
dynamicannotationdb/migration/alembic/versions/fac66b439033_add_view_model.py
tests/__init__.py
tests/conftest.py
tests/test_annotation.py
tests/test_database.py
tests/test_errors.py
tests/test_interface.py
tests/test_schema.py
tests/test_segmentation.py