Metadata-Version: 2.1
Name: DynamicAnnotationDB
Version: 5.13.1
Summary: Annotation Database pendant to the chunkedgraph
Home-page: https://github.com/seung-lab/DynamicAnnotationDB
Author: Sven Dorkenwald, Derrick Brittain
Author-email: sdorkenw@princeton.edu
Classifier: Programming Language :: Python :: 3
Classifier: License :: OSI Approved :: MIT License
Classifier: Operating System :: POSIX :: Linux
License-File: LICENSE
